meshagent/tools/__init__.py
meshagent/tools/blob.py
meshagent/tools/config.py
meshagent/tools/container_shell.py
meshagent/tools/database.py
meshagent/tools/datetime.py
meshagent/tools/discovery.py
meshagent/tools/document_tools.py
meshagent/tools/hosting.py
meshagent/tools/multi_tool.py
meshagent/tools/pydantic.py
meshagent/tools/script.py
meshagent/tools/storage.py
meshagent/tools/strict_schema.py
meshagent/tools/tool.py
meshagent/tools/toolkit.py
meshagent/tools/uuid.py
meshagent/tools/version.py
meshagent/tools/web_toolkit.py
meshagent/tools/tests/tool_decorator_test.py
meshagent_tools-0.25.1.dist-info/licenses/LICENSE
meshagent_tools-0.25.1.dist-info/METADATA
meshagent_tools-0.25.1.dist-info/WHEEL
meshagent_tools-0.25.1.dist-info/top_level.txt
meshagent_tools-0.25.1.dist-info/RECORD
