Metadata-Version: 2.4
Name: meshagent-tools
Version: 0.25.1
Summary: Tools for Meshagent
License-Expression: Apache-2.0
Project-URL: Documentation, https://docs.meshagent.com
Project-URL: Website, https://www.meshagent.com
Project-URL: Source, https://www.meshagent.com
Requires-Python: >=3.13
License-File: LICENSE
Requires-Dist: pyjwt~=2.10
Requires-Dist: pytest~=8.4
Requires-Dist: pytest-asyncio~=0.26
Requires-Dist: meshagent-api~=0.25.1
Requires-Dist: html-to-markdown~=2.24.3
Requires-Dist: aiohttp[speedups]~=3.13.0
Requires-Dist: opentelemetry-distro~=0.54b1
Dynamic: license-file
